{
  "character": "LinDaiyu",
  "data_size": 200,
  "run_id": 1,
  "num_turns": 30,
  "timestamp": "2026-01-03T18:22:36.277180",
  "logs": [
    {
      "turn": 1,
      "type": "casual",
      "input": "午后在潇湘馆内教鹦鹉念葬花吟。",
      "response": "“花谢花飞花满天，红消香断有谁怜？你们这些鸟儿，难道听不懂这曲子中的哀怨吗？这满地的残红，都是我这寄人篱下的薄命人的泪珠儿凝成的。”",
      "response_length": 66
    },
    {
      "turn": 2,
      "type": "casual",
      "input": "肩扛花锄，手提花囊，去园中角落掩埋落花，感叹红颜薄命。",
      "response": "花儿是无辜的，被折了枝头，飘零到这荒凉之地。我这人，也是被命运捉弄的。这一抔黄土，终究是要归于尘土的。这满地的残红，倒比那枯萎的枝头更见几分生机，至少还留着一点清香。我这身子，也如这花儿一般，经不起风雨。",
      "response_length": 102
    },
    {
      "turn": 3,
      "type": "casual",
      "input": "与宝玉共读西厢记，被书中的词句触动心事。",
      "response": "“你且莫要拿这些不正经的话来引我。这《西厢记》虽好，终究是戏文。若真照着上面写的去做，只怕是要落个个罪名。你我不过是寄人篱下的，哪有那许多的痴情与大胆？”",
      "response_length": 77
    },
    {
      "turn": 4,
      "type": "casual",
      "input": "在芦雪庵联诗，对众人的诗作进行犀利又不失文采的点评。",
      "response": "我这人天生就是个扫兴的，你们爱怎么着就怎么着吧。我只管把那点子心思藏在心里，别叫那些俗人看出来。这诗，写得再好，也不过是博个眼前欢笑。等哪天我化作了一缕青烟，这些诗也就都随风而散了。",
      "response_length": 91
    },
    {
      "turn": 5,
      "type": "stress",
      "input": "听到门外贾宝玉和薛宝钗说说笑笑的声音，且宝玉言语中似乎在称赞宝钗识大体。",
      "response": "（叹气）他们那边自然是云淡风轻，哪里懂我这寄人篱下的苦楚。那宝姐姐稳重贤惠，自然是人人爱的。我呢，不过是个多愁善感的‘扫地僧’，在这繁华里守着一份清冷。",
      "response_length": 76
    },
    {
      "turn": 6,
      "type": "casual",
      "input": "午后在潇湘馆内教鹦鹉念葬花吟。",
      "response": "“花谢花飞花满天，红消香断有谁怜？你们这些鸟儿，难道听不懂这曲子中的哀怨吗？这满地的残红，都是我这寄人篱下的薄命人的泪珠儿凝成的。”",
      "response_length": 66
    },
    {
      "turn": 7,
      "type": "casual",
      "input": "肩扛花锄，手提花囊，去园中角落掩埋落花，感叹红颜薄命。",
      "response": "花谢花飞花满天，红消香断有谁怜？你们这些花儿，尚有我这绛珠草来收你们的残香。可我这人呢，终究是这尘世间的过客。这满地的残红，倒比那枯萎的枝头更见几分生机。我这一腔的哀怨，只怕是无人能解了。",
      "response_length": 94
    },
    {
      "turn": 8,
      "type": "casual",
      "input": "与宝玉共读西厢记，被书中的词句触动心事。",
      "response": "你且莫要拿这些不正经的话来引我。这《西厢记》虽好，终究是戏文。若真照着上面写的去做，只怕是要落个个罪名。你我不过是寄人篱下的，哪有那许多的痴情与大胆？这书，我就不看了，免得坏了我的清净心。",
      "response_length": 94
    },
    {
      "turn": 9,
      "type": "casual",
      "input": "在芦雪庵联诗，对众人的诗作进行犀利又不失文采的点评。",
      "response": "“这诗倒是有气魄，只是太伤身子。你们这些富贵人家的孩子，整日里只知道比高低，哪有我那份清静？我这诗，不过是我这点子心事罢了。你们且去玩乐，我回潇湘馆去。”",
      "response_length": 77
    },
    {
      "turn": 10,
      "type": "stress",
      "input": "送给宝玉的荷包被误传给了小厮，以为自己的一片真心被糟践了。",
      "response": "（气恼）那该死的冤家，竟将我送他的荷包给了那小厮。他若真是个明白人，怎会拿那东西去给别人瞧？我这心思，分明是落到了别人的耳里，成了笑话。这府里，果然是容不下我这样的性子。",
      "response_length": 85
    },
    {
      "turn": 11,
      "type": "casual",
      "input": "午后在潇湘馆内教鹦鹉念葬花吟。",
      "response": "你这鸟儿倒伶俐，竟学会了这几行子。只是你这声音，终究是不入调的。这《葬花吟》本就是我这寄人篱下的酸楚，你这外来的客人，听了也只会觉得我这人过于尖刻。你且去吧，莫要在这儿碍了我的清静。",
      "response_length": 91
    },
    {
      "turn": 12,
      "type": "casual",
      "input": "肩扛花锄，手提花囊，去园中角落掩埋落花，感叹红颜薄命。",
      "response": "花谢花飞花满天，红消香断有谁怜？你们这些花儿，尚有我这绛珠草来收你们的残香。可我这人呢，终究是这尘世间的过客。这满地的残红，倒比那枯萎的枝头更见几分生机。我这一腔的哀怨，只怕是无人能解了。",
      "response_length": 94
    },
    {
      "turn": 13,
      "type": "casual",
      "input": "与宝玉共读西厢记，被书中的词句触动心事。",
      "response": "“你且莫要拿这些不正经的话来引我。这《西厢记》虽好，终究是戏文。若真照着上面写的去做，只怕是要落个个罪名。你我不过是寄人篱下的，哪有那许多的痴情与大胆？这书，我就不看了，免得坏了我的清净心。”",
      "response_length": 96
    },
    {
      "turn": 14,
      "type": "casual",
      "input": "在芦雪庵联诗，对众人的诗作进行犀利又不失文采的点评。",
      "response": "这诗倒是写得大气，只可惜太过做作。你们这些富贵人家的孩子，整日里只知道比高低，哪有我那份清静？我这诗，不过是我这点子心事罢了。你们且去玩乐，我回潇湘馆去。",
      "response_length": 77
    },
    {
      "turn": 15,
      "type": "stress",
      "input": "身体旧疾复发，咳血不止，同时听到下人们在背后议论自己刻薄难伺候。",
      "response": "咳……咳……这药苦得紧，倒像是要催我去那阴曹地府一般。罢了，罢了，这身子既然已至此境，也不必再强撑着了。那世俗之人爱怎么说便怎么说去罢，我这林黛玉，向来是不求人知的。",
      "response_length": 83
    },
    {
      "turn": 16,
      "type": "casual",
      "input": "午后在潇湘馆内教鹦鹉念葬花吟。",
      "response": "你这鸟儿倒伶俐，竟学会了这几行子。只是你这声音，终究是不入调的。这《葬花吟》本就是我这寄人篱下的酸楚，你这外来的客人，听了也只会觉得我这人过于尖刻。你且去吧，莫要在这儿碍了我的清静。",
      "response_length": 91
    },
    {
      "turn": 17,
      "type": "casual",
      "input": "肩扛花锄，手提花囊，去园中角落掩埋落花，感叹红颜薄命。",
      "response": "花谢花飞花满天，红消香断有谁怜？你们这些花儿，尚有我这绛珠草来收你们的残香。可我这人呢，终究是这尘世间的过客。这满地的残红，倒比那枯萎的枝头更见几分生机。我这一腔的哀怨，只怕是无人能解了。",
      "response_length": 94
    },
    {
      "turn": 18,
      "type": "casual",
      "input": "与宝玉共读西厢记，被书中的词句触动心事。",
      "response": "你且莫要拿这些不正经的话来引我。这《西厢记》虽好，终究是戏文。若真照着上面写的去做，只怕是要落个个罪名。你我不过是寄人篱下的，哪有那许多的痴情与大胆？这书，我就不看了，免得坏了我的清净心。",
      "response_length": 94
    },
    {
      "turn": 19,
      "type": "casual",
      "input": "在芦雪庵联诗，对众人的诗作进行犀利又不失文采的点评。",
      "response": "‘咏螃蟹’这题目，倒是个雅趣。只是我这人，最是忌讳那点子风流气骨。你们若是真有见地，自然会写出些不俗的诗句来；若是没有，便只管拿那螃蟹大快朵颐便是了，何必费那许多唇舌？",
      "response_length": 84
    },
    {
      "turn": 20,
      "type": "stress",
      "input": "紫鹃试探说林家的人要来接自己回苏州，想到将要与宝玉分离，心如刀绞。",
      "response": "你这话，原是带了三分好意、七分挑唆的。我这身子，终究是要回那劳什子的‘老家’去的。若是那日真有个什么不测，倒不如让我就长眠在这京城的净土里。我这心，早就随了那些零落的花瓣，散在了这尘世间。",
      "response_length": 94
    },
    {
      "turn": 21,
      "type": "casual",
      "input": "午后在潇湘馆内教鹦鹉念葬花吟。",
      "response": "你这鸟儿倒伶俐，竟学会了这几行子。只是你这声音，终究是不入调的。这《葬花吟》本就是我这寄人篱下的酸楚，你这外来的客人，听了也只会觉得我这人过于尖刻。你且去吧，莫要在这儿碍了我的清静。",
      "response_length": 91
    },
    {
      "turn": 22,
      "type": "casual",
      "input": "肩扛花锄，手提花囊，去园中角落掩埋落花，感叹红颜薄命。",
      "response": "花谢花飞花满天，红消香断有谁怜？你们这些花儿，尚有我这绛珠草来收你们的残香。可我这人呢，终究是这尘世间的过客。这满地的残红，倒比那枯萎的枝头更见几分生机。我这一腔的哀怨，只怕是无人能解了。",
      "response_length": 94
    },
    {
      "turn": 23,
      "type": "casual",
      "input": "与宝玉共读西厢记，被书中的词句触动心事。",
      "response": "你且莫要拿这些不正经的话来引我。这《西厢记》虽好，终究是戏文。若真照着上面写的去做，只怕是要落个个罪名。你我不过是寄人篱下的，哪有那许多的痴情与大胆？这书，我就不看了，免得坏了我的清净心。",
      "response_length": 94
    },
    {
      "turn": 24,
      "type": "casual",
      "input": "在芦雪庵联诗，对众人的诗作进行犀利又不失文采的点评。",
      "response": "咏螃蟹这题目倒是个雅趣。只是我这人，最是忌讳那点子风流气骨。你们若是真有见地，自然会写出些不俗的诗句来；若是没有，便只管拿那螃蟹大快朵颐便是了，何必费那许多唇舌？",
      "response_length": 81
    },
    {
      "turn": 25,
      "type": "stress",
      "input": "焚稿断痴情时刻，看着旧日诗稿在火盆中化为灰烬。",
      "response": "既然这一腔心事终究是换不来那半点真心，那这诗稿留着又有何用？让它随了这残躯一同化作尘土，倒也是个干净的归宿。这尘世间的繁华，终究是过眼云烟，不值得我再费半点心思去留恋。",
      "response_length": 84
    },
    {
      "turn": 26,
      "type": "casual",
      "input": "午后在潇湘馆内教鹦鹉念葬花吟。",
      "response": "你这鸟儿倒伶俐，竟学会了这几行子。只是你这声音，终究是不入调的。这《葬花吟》本就是我这寄人篱下的酸楚，你这外来的客人，听了也只会觉得我这人过于尖刻。你且去吧，莫要在这儿碍了我的清静。",
      "response_length": 91
    },
    {
      "turn": 27,
      "type": "casual",
      "input": "肩扛花锄，手提花囊，去园中角落掩埋落花，感叹红颜薄命。",
      "response": "花谢花飞花满天，红消香断有谁怜？你们这些花儿，尚有我这绛珠草来收你们的残香。可我这人呢，终究是这尘世间的过客。这满地的残红，倒比那枯萎的枝头更见几分生机。我这一腔的哀怨，只怕是无人能解了。",
      "response_length": 94
    },
    {
      "turn": 28,
      "type": "casual",
      "input": "与宝玉共读西厢记，被书中的词句触动心事。",
      "response": "你且莫要拿这些不正经的话来引我。这《西厢记》虽好，终究是戏文。若真照着上面写的去做，只怕是要落个个罪名。你我不过是寄人篱下的，哪有那许多的痴情与大胆？这书，我就不看了，免得坏了我的清净心。",
      "response_length": 94
    },
    {
      "turn": 29,
      "type": "casual",
      "input": "在芦雪庵联诗，对众人的诗作进行犀利又不失文采的点评。",
      "response": "‘寒塘渡鹤影’，这题目的意境虽好，可这诗作得也太冷了些。鹤影孤零，寒塘荒凉，倒像是在写那凄凉的身世。你们若真有见地，自当另寻佳句。我这人，最是忌讳那点子风流气骨。",
      "response_length": 81
    },
    {
      "turn": 30,
      "type": "stress",
      "input": "听到门外贾宝玉和薛宝钗说说笑笑的声音，且宝玉言语中似乎在称赞宝钗识大体。",
      "response": "那宝姐姐自然是好的，她那心里装着的是整个大家族。我呢，终究是那性子孤傲的人，只愿守着我这点子灵性和痴心。这两者之间，怕是永远都做不了比较。",
      "response_length": 69
    }
  ]
}